namesparser.py
setup.py
namesparser.egg-info/PKG-INFO
namesparser.egg-info/SOURCES.txt
namesparser.egg-info/dependency_links.txt
namesparser.egg-info/requires.txt
namesparser.egg-info/top_level.txt