Metadata-Version: 1.1
Name: namesparser
Version: 1.0.0
Summary: Complement to nameparser for parsing lists of names.
Home-page: https://github.com/gwu-libraries/namesparser
Author: Justin Littman
Author-email: justinlittman@gmail.com
License: UNKNOWN
Platform: POSIX
Classifier: Intended Audience :: Developers
Classifier: Topic :: Software Development :: Libraries :: Python Modules
Classifier: Programming Language :: Python :: 2.7
Classifier: Development Status :: 4 - Beta
